num.py
timing.py
txt.py
putools-1.25.dist-info/LICENSE
putools-1.25.dist-info/METADATA
putools-1.25.dist-info/WHEEL
putools-1.25.dist-info/top_level.txt
putools-1.25.dist-info/RECORD
